pycparser-stubs/__init__.pyi
pycparser-stubs/c_ast.pyi
pycparser-stubs/c_generator.pyi
pycparser-stubs/c_lexer.pyi
pycparser-stubs/c_parser.pyi
pycparser-stubs/py.typed
pycparser_stubs-0.0.1.dist-info/LICENSE
pycparser_stubs-0.0.1.dist-info/METADATA
pycparser_stubs-0.0.1.dist-info/WHEEL
pycparser_stubs-0.0.1.dist-info/top_level.txt
pycparser_stubs-0.0.1.dist-info/RECORD
