Metadata-Version: 2.1
Name: pycparser-stubs
Version: 0.0.1
Summary: PEP 561 type stubs for pycparser
Home-page: https://github.com/TsXor/pycparser-stubs
Author: TsXor
License: MIT License
Classifier: License :: OSI Approved :: MIT License
Requires-Python: >=3.5
License-File: LICENSE
Requires-Dist: pycparser (>=2.21)
